py_arp
