Metadata-Version: 2.1
Name: py-arp
Version: 0.0.1
Summary: Quick and dirty arp scan, save results to a file
Home-page: https://github.com/deadlift1226/py_arp
Author: Dane Morgan
Author-email: danemorgan91@gmail.com
License: UNKNOWN
Platform: UNKNOWN
Classifier: Programming Language :: Python :: 3
Classifier: License :: OSI Approved :: MIT License
Classifier: Operating System :: OS Independent
